<list>
  <CompomentBean>
    <rgb16>#FFFFFF</rgb16>
    <bgRgb16>#FFFFFF</bgRgb16>
    <x>48</x>
    <y>368</y>
    <w>551</w>
    <h>58</h>
    <cnname>bg1427190649625</cnname>
    <enname>bg1427190649625LinearLayout</enname>
    <textSize>16</textSize>
    <isImgCache>false</isImgCache>
    <isPublicCompoment>false</isPublicCompoment>
    <type>LinearLayout</type>
    <orientation></orientation>
    <gravity></gravity>
    <relative></relative>
    <picName>图片名</picName>
    <time>1427190651562</time>
  </CompomentBean>
  <CompomentBean>
    <rgb16>#E6E7E1</rgb16>
    <bgRgb16>#背景颜色</bgRgb16>
    <x>76</x>
    <y>383</y>
    <w>495</w>
    <h>25</h>
    <cnname>bb</cnname>
    <enname>bbTextView</enname>
    <textSize>16</textSize>
    <isImgCache>false</isImgCache>
    <isPublicCompoment>false</isPublicCompoment>
    <type>TextView</type>
    <orientation></orientation>
    <gravity></gravity>
    <relative></relative>
    <picName>图片名</picName>
    <time>1427190664765</time>
  </CompomentBean>
</list>